fen2pil/VERSION
fen2pil/__init__.py
fen2pil/draw.py
fen2pil/pieces/black/b.png
fen2pil/pieces/black/k.png
fen2pil/pieces/black/n.png
fen2pil/pieces/black/p.png
fen2pil/pieces/black/q.png
fen2pil/pieces/black/r.png
fen2pil/pieces/white/b.png
fen2pil/pieces/white/k.png
fen2pil/pieces/white/n.png
fen2pil/pieces/white/p.png
fen2pil/pieces/white/q.png
fen2pil/pieces/white/r.png
fen2pil-0.3.0.dist-info/LICENSE
fen2pil-0.3.0.dist-info/METADATA
fen2pil-0.3.0.dist-info/WHEEL
fen2pil-0.3.0.dist-info/top_level.txt
fen2pil-0.3.0.dist-info/RECORD
