Metadata-Version: 2.1
Name: fen2pil
Version: 0.3.0
Summary: Convert Forsyth–Edwards Notation (FEN) to a 2D chessboard PIL image
Home-page: https://github.com/elbuco1/fen2pil
Author: Laurent Boucaud
Author-email: lrtboucaud@gmail.com
Classifier: License :: OSI Approved :: MIT License
Classifier: Programming Language :: Python :: 3.7
Classifier: Programming Language :: Python :: 3.8
Classifier: Programming Language :: Python :: 3.9
Classifier: Programming Language :: Python :: 3 :: Only
Requires-Python: >=3.7
License-File: LICENSE
Requires-Dist: numpy (>=1)
Requires-Dist: chess (>=1)
Requires-Dist: opencv-python (>=4)
Requires-Dist: Pillow (>=8)
Provides-Extra: tests
Requires-Dist: pytest ; extra == 'tests'
Requires-Dist: tox ; extra == 'tests'
